anyset/__init__.py
anyset/adapters/__init__.py
anyset/adapters/repository/__init__.py
anyset/adapters/repository/postgres/__init__.py
anyset/adapters/repository/postgres/adapter.py
anyset/adapters/repository/postgres/settings.py
anyset/adapters/repository/snowflake/__init__.py
anyset/adapters/repository/snowflake/adapter.py
anyset/adapters/repository/snowflake/settings.py
anyset/core/__init__.py
anyset/core/dependencies.py
anyset/core/models.py
anyset/core/repository_interface.py
anyset/core/router.py
anyset/core/settings.py
anyset/core/singleton_meta.py
anyset-0.1.4.dist-info/METADATA
anyset-0.1.4.dist-info/WHEEL
anyset-0.1.4.dist-info/top_level.txt
anyset-0.1.4.dist-info/RECORD
