Metadata-Version: 2.4
Name: anyset
Version: 0.1.4
Summary: AnySet is a Python library designed to accelerate backend development for data visualization applications, emphasizing extensibility and rapid iteration.
Author-email: buffolander <brdu1976@gmail.com>
Requires-Python: >=3.12
Requires-Dist: fastapi==0.115.11
Requires-Dist: orjson>=3.10.15
Requires-Dist: pandas>=2.2.3
Requires-Dist: pydantic-settings>=2.1.0
Requires-Dist: pydantic>=2.6.0
Requires-Dist: python-dotenv>=1.0.1
Requires-Dist: python-slugify>=8.0.4
Requires-Dist: sqlalchemy>=2.0.40
Requires-Dist: tomli>=2.2.1
Provides-Extra: postgres
Requires-Dist: psycopg2-binary>=2.9.10; extra == "postgres"
Provides-Extra: snowflake
Requires-Dist: snowflake-connector-python>=3.14.0; extra == "snowflake"
Requires-Dist: snowflake-sqlalchemy>=1.7.3; extra == "snowflake"
